swh/__init__.py
swh/spdx/__init__.py
swh/spdx/bar.py
swh/spdx/cli.py
swh/spdx/py.typed
swh/spdx/tests/__init__.py
swh/spdx/tests/test_nothing.py
swh.spdx-0.0.0.dist-info/AUTHORS
swh.spdx-0.0.0.dist-info/LICENSE
swh.spdx-0.0.0.dist-info/METADATA
swh.spdx-0.0.0.dist-info/WHEEL
swh.spdx-0.0.0.dist-info/top_level.txt
swh.spdx-0.0.0.dist-info/RECORD
