Metadata-Version: 2.1
Name: swh.spdx
Version: 0.0.0
Summary: Software Heritage <SPDX Generation>
Home-page: https://gitlab.softwareheritage.org/swh/devel/swh-spdx
Author: Software Heritage developers
Author-email: swh-devel@inria.fr
Project-URL: Bug Reports, https://gitlab.softwareheritage.org/swh/devel/swh-spdx/-/issues
Project-URL: Funding, https://www.softwareheritage.org/donate
Project-URL: Source, https://gitlab.softwareheritage.org/swh/devel/swh-spdx
Project-URL: Documentation, https://docs.softwareheritage.org/devel/swh-spdx/
Classifier: Programming Language :: Python :: 3
Classifier: Intended Audience :: Developers
Classifier: License :: OSI Approved :: GNU General Public License v3 (GPLv3)
Classifier: Operating System :: OS Independent
Classifier: Development Status :: 3 - Alpha
Requires-Python: >=3.7
License-File: LICENSE
License-File: AUTHORS
Requires-Dist: swh.core[http] (>=0.3)
Provides-Extra: testing
Requires-Dist: pytest ; extra == 'testing'
